onyx.datafeeds-2.1.6-py3.9-nspkg.pth
onyx/datafeeds/__init__.py
onyx/datafeeds/clients.py
onyx/datafeeds/exceptions.py
onyx/datafeeds/routerlib.py
onyx/datafeeds/serverlib.py
onyx/datafeeds/utils.py
onyx/datafeeds/bloomberg/__init__.py
onyx/datafeeds/bloomberg/blp_api.py
onyx/datafeeds/bloomberg/com_api.py
onyx/datafeeds/bloomberg/com_helpers.py
onyx/datafeeds/bloomberg/utils.py
onyx/datafeeds/google/__init__.py
onyx/datafeeds/google/google_finance.py
onyx/datafeeds/oanda/__init__.py
onyx/datafeeds/oanda/oanda.py
onyx/datafeeds/openexchangerates/__init__.py
onyx/datafeeds/openexchangerates/openexchangerates.py
onyx/datafeeds/procs/keepalive.py
onyx/datafeeds/procs/router.py
onyx/datafeeds/procs/server.py
onyx/datafeeds/test/__init__.py
onyx/datafeeds/test/test_bbg_com_api.py
onyx/datafeeds/wsj/__init__.py
onyx/datafeeds/wsj/wsj.py
onyx/datafeeds/yahoo/__init__.py
onyx/datafeeds/yahoo/yahoo_finance.py
onyx.datafeeds-2.1.6.dist-info/LICENSE.txt
onyx.datafeeds-2.1.6.dist-info/METADATA
onyx.datafeeds-2.1.6.dist-info/WHEEL
onyx.datafeeds-2.1.6.dist-info/entry_points.txt
onyx.datafeeds-2.1.6.dist-info/namespace_packages.txt
onyx.datafeeds-2.1.6.dist-info/top_level.txt
onyx.datafeeds-2.1.6.dist-info/RECORD
