Metadata-Version: 2.1
Name: onyx.datafeeds
Version: 2.1.6
Summary: Datafeeds extensions for onyx.
Home-page: https://github.com/sbraccia/onyx.datafeeds
Author: carlo sbraccia
Author-email: carlo.sbraccia@gmail.com
License: UNKNOWN
Platform: UNKNOWN
Classifier: Development Status :: 6 - Mature
Classifier: Environment :: Console
Classifier: Intended Audience :: Developers
Classifier: Intended Audience :: Financial and Insurance Industry
Classifier: License :: OSI Approved :: Apache Software License
Classifier: Natural Language :: English
Classifier: Operating System :: OS Independent
Classifier: Programming Language :: Python :: 3.5
Classifier: Topic :: Software Development :: Libraries :: Python Modules
Classifier: Topic :: Software Development :: Libraries :: Application Frameworks
License-File: LICENSE.txt
Requires-Dist: onyx.core
Requires-Dist: argh
Requires-Dist: tornado
Requires-Dist: requests
Requires-Dist: asyncmc
Requires-Dist: python-memcached
Provides-Extra: win32
Requires-Dist: blpapi ; extra == 'win32'
Requires-Dist: comtypes ; extra == 'win32'
Requires-Dist: pywin32 ; extra == 'win32'
